wokwi_client/__init__.py
wokwi_client/__main__.py
wokwi_client/__version__.py
wokwi_client/client.py
wokwi_client/client_sync.py
wokwi_client/client_sync.pyi
wokwi_client/constants.py
wokwi_client/control.py
wokwi_client/event_queue.py
wokwi_client/exceptions.py
wokwi_client/file_ops.py
wokwi_client/framebuffer.py
wokwi_client/idf.py
wokwi_client/models.py
wokwi_client/pins.py
wokwi_client/protocol_types.py
wokwi_client/serial.py
wokwi_client/simulation.py
wokwi_client/transport.py
wokwi_client/vcd.py
wokwi_client/cli/__init__.py
wokwi_client-0.3.0.dist-info/METADATA
wokwi_client-0.3.0.dist-info/WHEEL
wokwi_client-0.3.0.dist-info/entry_points.txt
wokwi_client-0.3.0.dist-info/licenses/LICENSE
wokwi_client-0.3.0.dist-info/RECORD
