Metadata-Version: 2.4
Name: wokwi-client
Version: 0.3.0
Summary: Typed Python SDK for the Wokwi Simulation API with both async and synchronous interfaces
Project-URL: Documentation, https://github.com/wokwi/wokwi-python-client#readme
Project-URL: Issues, https://github.com/wokwi/wokwi-python-client/issues
Project-URL: Source, https://github.com/wokwi/wokwi-python-client
Author-email: Uri Shaked <uri@wokwi.com>
License-Expression: MIT
License-File: LICENSE
Keywords: api,arduino,asyncio,avr,esp32,python,rp2040,simulation,wokwi
Classifier: Development Status :: 3 - Alpha
Classifier: License :: OSI Approved :: MIT License
Classifier: Programming Language :: Python :: 3
Classifier: Programming Language :: Python :: 3 :: Only
Classifier: Programming Language :: Python :: 3.9
Classifier: Programming Language :: Python :: 3.10
Classifier: Programming Language :: Python :: 3.11
Classifier: Programming Language :: Python :: 3.12
Classifier: Programming Language :: Python :: 3.13
Classifier: Topic :: Software Development :: Embedded Systems
Classifier: Topic :: System :: Emulators
Classifier: Typing :: Typed
Requires-Python: >=3.9
Requires-Dist: pydantic>=2.8
Requires-Dist: websockets<13,>=12
Provides-Extra: cli
Requires-Dist: click<9,>=8.1; extra == 'cli'
Requires-Dist: typer[all]>=0.12; extra == 'cli'
Requires-Dist: types-click; extra == 'cli'
